aliyunsdkdomain/__init__.py
aliyunsdkdomain/endpoint.py
aliyunsdkdomain/request/__init__.py
aliyunsdkdomain/request/v20180129/AcknowledgeTaskResultRequest.py
aliyunsdkdomain/request/v20180129/BatchFuzzyMatchDomainSensitiveWordRequest.py
aliyunsdkdomain/request/v20180129/CancelDomainVerificationRequest.py
aliyunsdkdomain/request/v20180129/CancelOperationAuditRequest.py
aliyunsdkdomain/request/v20180129/CancelQualificationVerificationRequest.py
aliyunsdkdomain/request/v20180129/CancelTaskRequest.py
aliyunsdkdomain/request/v20180129/ChangeResourceGroupRequest.py
aliyunsdkdomain/request/v20180129/CheckDomainRequest.py
aliyunsdkdomain/request/v20180129/CheckDomainSunriseClaimRequest.py
aliyunsdkdomain/request/v20180129/CheckIntlFixPriceDomainStatusRequest.py
aliyunsdkdomain/request/v20180129/CheckMaxYearOfServerLockRequest.py
aliyunsdkdomain/request/v20180129/CheckProcessingServerLockApplyRequest.py
aliyunsdkdomain/request/v20180129/CheckTransferInFeasibilityRequest.py
aliyunsdkdomain/request/v20180129/ConfirmTransferInEmailRequest.py
aliyunsdkdomain/request/v20180129/CreateIntlFixedPriceDomainOrderRequest.py
aliyunsdkdomain/request/v20180129/DeleteContactTemplatesRequest.py
aliyunsdkdomain/request/v20180129/DeleteDomainGroupRequest.py
aliyunsdkdomain/request/v20180129/DeleteEmailVerificationRequest.py
aliyunsdkdomain/request/v20180129/DeleteRegistrantProfileRequest.py
aliyunsdkdomain/request/v20180129/DomainSpecialBizCancelRequest.py
aliyunsdkdomain/request/v20180129/EmailVerifiedRequest.py
aliyunsdkdomain/request/v20180129/FuzzyMatchDomainSensitiveWordRequest.py
aliyunsdkdomain/request/v20180129/GetIntlFixPriceDomainListUrlRequest.py
aliyunsdkdomain/request/v20180129/GetOperationOssUploadPolicyRequest.py
aliyunsdkdomain/request/v20180129/GetQualificationUploadPolicyRequest.py
aliyunsdkdomain/request/v20180129/ListEmailVerificationRequest.py
aliyunsdkdomain/request/v20180129/ListServerLockRequest.py
aliyunsdkdomain/request/v20180129/LookupTmchNoticeRequest.py
aliyun_python_sdk_domain-3.14.11.dist-info/LICENSE
aliyun_python_sdk_domain-3.14.11.dist-info/METADATA
aliyun_python_sdk_domain-3.14.11.dist-info/WHEEL
aliyun_python_sdk_domain-3.14.11.dist-info/top_level.txt
aliyun_python_sdk_domain-3.14.11.dist-info/RECORD
